async_cow
